arcade_mcp_server/__init__.py
arcade_mcp_server/__main__.py
arcade_mcp_server/context.py
arcade_mcp_server/convert.py
arcade_mcp_server/exceptions.py
arcade_mcp_server/lifespan.py
arcade_mcp_server/logging_utils.py
arcade_mcp_server/mcp_app.py
arcade_mcp_server/py.typed
arcade_mcp_server/server.py
arcade_mcp_server/session.py
arcade_mcp_server/settings.py
arcade_mcp_server/types.py
arcade_mcp_server/worker.py
arcade_mcp_server/auth/__init__.py
arcade_mcp_server/fastapi/__init__.py
arcade_mcp_server/fastapi/auth_routes.py
arcade_mcp_server/fastapi/middleware.py
arcade_mcp_server/fastapi/routes.py
arcade_mcp_server/managers/__init__.py
arcade_mcp_server/managers/base.py
arcade_mcp_server/managers/prompt.py
arcade_mcp_server/managers/resource.py
arcade_mcp_server/managers/tool.py
arcade_mcp_server/middleware/__init__.py
arcade_mcp_server/middleware/base.py
arcade_mcp_server/middleware/error_handling.py
arcade_mcp_server/middleware/logging.py
arcade_mcp_server/resource_server/README.md
arcade_mcp_server/resource_server/__init__.py
arcade_mcp_server/resource_server/base.py
arcade_mcp_server/resource_server/middleware.py
arcade_mcp_server/resource_server/validators/__init__.py
arcade_mcp_server/resource_server/validators/auth.py
arcade_mcp_server/resource_server/validators/jwks.py
arcade_mcp_server/transports/__init__.py
arcade_mcp_server/transports/http_session_manager.py
arcade_mcp_server/transports/http_streamable.py
arcade_mcp_server/transports/stdio.py
arcade_mcp_server/usage/__init__.py
arcade_mcp_server/usage/constants.py
arcade_mcp_server/usage/server_tracker.py
arcade_mcp_server-1.15.2.dist-info/METADATA
arcade_mcp_server-1.15.2.dist-info/WHEEL
arcade_mcp_server-1.15.2.dist-info/RECORD
