Metadata-Version: 2.4
Name: arcade-mcp-server
Version: 1.15.2
Summary: Model Context Protocol (MCP) server framework for Arcade.dev
Author: Arcade.dev
License: MIT
Classifier: Development Status :: 5 - Production/Stable
Classifier: Intended Audience :: Developers
Classifier: License :: OSI Approved :: MIT License
Classifier: Programming Language :: Python :: 3
Classifier: Programming Language :: Python :: 3.10
Classifier: Programming Language :: Python :: 3.11
Classifier: Programming Language :: Python :: 3.12
Classifier: Programming Language :: Python :: 3.13
Requires-Python: >=3.10
Requires-Dist: anyio>=4.0.0
Requires-Dist: arcade-core<5.0.0,>=4.2.2
Requires-Dist: arcade-serve<4.0.0,>=3.2.0
Requires-Dist: arcade-tdk<4.0.0,>=3.4.0
Requires-Dist: arcadepy>=1.5.0
Requires-Dist: fastapi>=0.100.0
Requires-Dist: httpx<1.0.0,>=0.27.0
Requires-Dist: joserfc>=1.5.0
Requires-Dist: pydantic-settings>=2.10.1
Requires-Dist: pydantic>=2.0.0
Requires-Dist: python-dotenv>=1.0.0
Requires-Dist: sse-starlette>=2.0.0
Requires-Dist: starlette>=0.37.0
Requires-Dist: uvicorn>=0.30.0
Requires-Dist: watchfiles>=0.18.0
Provides-Extra: dev
Requires-Dist: mypy>=1.0.0; extra == 'dev'
Requires-Dist: pytest-asyncio>=0.23.0; extra == 'dev'
Requires-Dist: pytest>=8.0.0; extra == 'dev'
Requires-Dist: ruff>=0.1.0; extra == 'dev'
